tidypy/__init__.py
tidypy/__main__.py
tidypy/cli.py
tidypy/collector.py
tidypy/config.py
tidypy/core.py
tidypy/extenders/__init__.py
tidypy/extenders/base.py
tidypy/extenders/bitbucket.py
tidypy/extenders/bitbucket_snippet.py
tidypy/extenders/filesys.py
tidypy/extenders/github.py
tidypy/extenders/github_gist.py
tidypy/extenders/gitlab.py
tidypy/extenders/gitlab_snippet.py
tidypy/extenders/pastebin.py
tidypy/finder.py
tidypy/plugin/__init__.py
tidypy/plugin/git.py
tidypy/plugin/mercurial.py
tidypy/plugin/nose.py
tidypy/plugin/pbbt.py
tidypy/plugin/pytest.py
tidypy/progress.py
tidypy/reports/__init__.py
tidypy/reports/base.py
tidypy/reports/console.py
tidypy/reports/custom.py
tidypy/reports/null.py
tidypy/reports/pycodestyle.py
tidypy/reports/pylint.py
tidypy/reports/structured.py
tidypy/tools/__init__.py
tidypy/tools/bandit.py
tidypy/tools/base.py
tidypy/tools/dlint.py
tidypy/tools/eradicate.py
tidypy/tools/jsonlint.py
tidypy/tools/manifest.py
tidypy/tools/mccabe.py
tidypy/tools/polint.py
tidypy/tools/pycodestyle.py
tidypy/tools/pydiatra.py
tidypy/tools/pydocstyle.py
tidypy/tools/pyflakes.py
tidypy/tools/pylint.py
tidypy/tools/pyroma.py
tidypy/tools/rstlint.py
tidypy/tools/secrets.py
tidypy/tools/vulture.py
tidypy/tools/yamllint.py
tidypy/util.py
tidypy-0.22.0.dist-info/entry_points.txt
tidypy-0.22.0.dist-info/LICENSE.rst
tidypy-0.22.0.dist-info/WHEEL
tidypy-0.22.0.dist-info/METADATA
tidypy-0.22.0.dist-info/RECORD
