Metadata-Version: 2.1
Name: tidypy
Version: 0.22.0
Summary: A tool that executes a suite of static analysis tools upon a Python project.
Home-page: https://github.com/jayclassless/tidypy
License: MIT
Keywords: tidypy,lint,linter,static analysis,pep8,pep257,pylint
Author: Jason Simeone
Author-email: jay@classless.net
Requires-Python: >=3.6,<4.0
Classifier: Development Status :: 4 - Beta
Classifier: Environment :: Console
Classifier: Framework :: Pytest
Classifier: Intended Audience :: Developers
Classifier: License :: OSI Approved :: MIT License
Classifier: Programming Language :: Python :: 3
Classifier: Programming Language :: Python :: 3.6
Classifier: Programming Language :: Python :: 3.7
Classifier: Programming Language :: Python :: 3.8
Classifier: Programming Language :: Python :: 3.9
Classifier: Topic :: Software Development
Classifier: Topic :: Software Development :: Quality Assurance
Classifier: Topic :: Software Development :: Testing
Requires-Dist: bandit (>=1.4,<2)
Requires-Dist: basicserial (>=0.1,<2.0)
Requires-Dist: check-manifest (>=0.42,<0.48)
Requires-Dist: click (>=6,<9)
Requires-Dist: demjson3 (>3,<4)
Requires-Dist: dennis (>=0.9,<1)
Requires-Dist: detect-secrets (>=1,<2)
Requires-Dist: dlint (>=0.8,<0.13)
Requires-Dist: eradicate (>=2,<3)
Requires-Dist: mccabe (>=0.6,<0.7)
Requires-Dist: pep8-naming (>=0.4,<0.13)
Requires-Dist: pycodestyle (>=2.4,<2.9)
Requires-Dist: pydiatra (>=0.12.2,<0.13)
Requires-Dist: pydocstyle (>=4,<7)
Requires-Dist: pyflakes (>=1.5,<2.5)
Requires-Dist: pylint (>=2,<2.12)
Requires-Dist: pyroma (>=2.2,<4)
Requires-Dist: pyyaml (>=3.12,<7)
Requires-Dist: requests (>=2,<3)
Requires-Dist: restructuredtext-lint (>=1.1,<2)
Requires-Dist: toml (>=0.10,<0.11)
Requires-Dist: tqdm (>=4.11,<5)
Requires-Dist: vulture (>=2.2,<3)
Requires-Dist: yamllint (>=1.8,<2)
